{
  "db_name": "PostgreSQL",
  "query": "\n            INSERT INTO ranking_records (user_id, collection_id, score, correct_count, total_questions, total_time_millis)\n            VALUES ($1, $2, $3, $4, $5, $6)\n            ",
  "describe": {
    "columns": [],
    "parameters": {
      "Left": [
        "Uuid",
        "Uuid",
        "Int4",
        "Int4",
        "Int4",
        "Int8"
      ]
    },
    "nullable": []
  },
  "hash": "250230448b6403e47b23316be2083bb90096a699b0bb99b3f3c3fb50d3cf868f"
}
